guetzli_recursively.py
guetzli_recursively-1.3.0.dist-info/LICENSE.txt
guetzli_recursively-1.3.0.dist-info/METADATA
guetzli_recursively-1.3.0.dist-info/WHEEL
guetzli_recursively-1.3.0.dist-info/entry_points.txt
guetzli_recursively-1.3.0.dist-info/top_level.txt
guetzli_recursively-1.3.0.dist-info/RECORD
