Metadata-Version: 2.1
Name: guetzli-recursively
Version: 1.3.0
Summary: Script in Python to convert all the jpeg of a folder recursively with Guetzli.
Home-page: https://github.com/tanrax/guetzli-recursively
Author: Andros Fenollosa
Author-email: andros@fenollosa.email
License: UNKNOWN
Keywords: guetzli,jpeg,recursive
Platform: UNKNOWN
Requires-Dist: Click (>=6.7)
